README.md
setup.cfg
setup.py
excel_writer/__init__.py
excel_writer/excel_writer.py
excel_writer.egg-info/PKG-INFO
excel_writer.egg-info/SOURCES.txt
excel_writer.egg-info/dependency_links.txt
excel_writer.egg-info/requires.txt
excel_writer.egg-info/top_level.txt