Metadata-Version: 2.1
Name: excel-writer
Version: 1.0.5
Summary: Simple library to write excel files from Python Dictionary or Pandas DataFrame.
Home-page: https://github.com/encoresky/excel-writer
Author: EncoreSky Technologies
Author-email: coontact@encoresky.com
License: MIT
